bert4tf2/__init__.py
bert4tf2/backend.py
bert4tf2/bert.py
bert4tf2/layers.py
bert4tf2/snippets.py
bert4tf2/tokenizer.py
bert4tf2-0.0.2.dist-info/LICENSE
bert4tf2-0.0.2.dist-info/METADATA
bert4tf2-0.0.2.dist-info/WHEEL
bert4tf2-0.0.2.dist-info/top_level.txt
bert4tf2-0.0.2.dist-info/RECORD
